CMakeLists.txt
LICENSE
MANIFEST.in
README.md
bindings.cpp
pyproject.toml
setup.py
ctc_loss/ctc_loss.h
ctc_loss/ctc_loss.metal
ctc_loss/ctc_loss_cpu.cpp
ctc_loss/ctc_loss_gpu.cpp
ctc_loss/ctc_loss_impl.h
ctc_loss/ctc_loss_inst.cpp
mlx_ctc/__init__.py
mlx_ctc/_ext.pyi
mlx_ctc.egg-info/PKG-INFO
mlx_ctc.egg-info/SOURCES.txt
mlx_ctc.egg-info/dependency_links.txt
mlx_ctc.egg-info/not-zip-safe
mlx_ctc.egg-info/requires.txt
mlx_ctc.egg-info/top_level.txt