Metadata-Version: 2.1
Name: mlx_ctc
Version: 0.0.1
Summary: C++ and Metal extensions for MLX CTC Loss
Author-email: Yury Popov <dev@phoenix.dj>
Project-URL: Homepage, https://github.com/djphoenix/mlx-ctc
Project-URL: Issues, https://github.com/djphoenix/mlx-ctc/issues
Classifier: Development Status :: 3 - Alpha
Classifier: Programming Language :: Python :: 3
Classifier: Programming Language :: C++
Classifier: License :: OSI Approved :: MIT License
Classifier: Operating System :: OS Independent
Requires-Python: >=3.8
License-File: LICENSE
Provides-Extra: dev
